collectd_top/__init__.py
collectd_top/collectd_plugin.py
collectd_top-0.0.1.dist-info/METADATA
collectd_top-0.0.1.dist-info/WHEEL
collectd_top-0.0.1.dist-info/top_level.txt
collectd_top-0.0.1.dist-info/RECORD
