Metadata-Version: 2.1
Name: collectd-top
Version: 0.0.1
Summary: CollectD plugin for top processes statistics
Home-page: https://github.com/gaurapanasenko/collectd-top
Author: Yehor Panasenko
Author-email: yehor.panasenko@gmail.com
License: UNKNOWN
Keywords: collectd-top
Platform: UNKNOWN
Requires-Dist: collectd
